{
  "date": "2026-05-15",
  "generated_at": "2026-05-15T22:01:34Z",
  "version": "1.0",
  "config": {
    "target_invested_ratio": 1.0,
    "min_invested_ratio": 0.98,
    "auto_execute": true
  },
  "account_equity": 93785.92,
  "portfolio_value": 93785.92,
  "cash": 236291.57000000004,
  "buying_power": 283184.53,
  "account_blocked": false,
  "trading_blocked": false,
  "current_positions": [
    {
      "symbol": "AMD",
      "asset_class": "us_equity",
      "side": "long",
      "qty": 33.0,
      "avg_entry_price": 432.69,
      "current_price": 423.1,
      "market_value": 13962.3,
      "unrealized_pl": -316.47,
      "pl_pct": -2.22,
      "pct_equity": 14.89
    },
    {
      "symbol": "GLD",
      "asset_class": "us_equity",
      "side": "long",
      "qty": 44.0,
      "avg_entry_price": 418.4639,
      "current_price": 417.05,
      "market_value": 18350.2,
      "unrealized_pl": -62.21,
      "pl_pct": -0.34,
      "pct_equity": 19.57
    },
    {
      "symbol": "NVDA",
      "asset_class": "us_equity",
      "side": "long",
      "qty": 64.0,
      "avg_entry_price": 226.7447,
      "current_price": 224.79,
      "market_value": 14386.56,
      "unrealized_pl": -125.1,
      "pl_pct": -0.86,
      "pct_equity": 15.34
    },
    {
      "symbol": "QQQ",
      "asset_class": "us_equity",
      "side": "long",
      "qty": 22.0,
      "avg_entry_price": 712.2782,
      "current_price": 707.67,
      "market_value": 15568.74,
      "unrealized_pl": -101.38,
      "pl_pct": -0.65,
      "pct_equity": 16.6
    },
    {
      "symbol": "SMH",
      "asset_class": "us_equity",
      "side": "long",
      "qty": 26.0,
      "avg_entry_price": 559.07,
      "current_price": 554.83,
      "market_value": 14425.58,
      "unrealized_pl": -110.24,
      "pl_pct": -0.76,
      "pct_equity": 15.38
    },
    {
      "symbol": "SPY",
      "asset_class": "us_equity",
      "side": "long",
      "qty": 24.0,
      "avg_entry_price": 741.6188,
      "current_price": 739.17,
      "market_value": 17740.08,
      "unrealized_pl": -58.77,
      "pl_pct": -0.33,
      "pct_equity": 18.92
    }
  ],
  "invested_ratio_before": 1.0069,
  "defensive_mode_active": false,
  "kill_switch_armed": false,
  "market_regime": "NEUTRAL",
  "regime_source": "auto",
  "allowed_buckets": [
    "ai_nasdaq_semis",
    "inflation_energy",
    "crypto"
  ],
  "regime_size_mult": 0.7,
  "scored_universe": [
    {
      "ticker": "USO",
      "score": 0.535,
      "components": {
        "momentum_5d": 0.546,
        "momentum_10d": 0.112,
        "momentum_20d": 0.554,
        "relative_strength": 1.0,
        "volume_expansion": -0.295,
        "breakout_flag": 1.0,
        "trend_filter": 1.0,
        "volatility_penalty": -0.0
      },
      "atr_pct": 0.0471,
      "tradeable": true,
      "reason": "long_setup: mom20=+27.7%, RS=+23.6%, breakout, uptrend",
      "bucket": "inflation_energy"
    },
    {
      "ticker": "AMD",
      "score": 0.418,
      "components": {
        "momentum_5d": -0.342,
        "momentum_10d": 0.528,
        "momentum_20d": 1.0,
        "relative_strength": 1.0,
        "volume_expansion": -0.196,
        "breakout_flag": 0.0,
        "trend_filter": 1.0,
        "volatility_penalty": -0.0
      },
      "atr_pct": 0.0738,
      "tradeable": true,
      "reason": "long_setup: mom20=+52.3%, RS=+48.3%, uptrend",
      "bucket": "ai_nasdaq_semis"
    },
    {
      "ticker": "OXY",
      "score": 0.35,
      "components": {
        "momentum_5d": 0.622,
        "momentum_10d": 0.045,
        "momentum_20d": 0.217,
        "relative_strength": 0.337,
        "volume_expansion": 0.163,
        "breakout_flag": 1.0,
        "trend_filter": 0.0,
        "volatility_penalty": -0.0
      },
      "atr_pct": 0.0346,
      "tradeable": false,
      "reason": "long_setup: mom20=+10.8%, RS=+6.7%, breakout",
      "bucket": "inflation_energy"
    },
    {
      "ticker": "SMH",
      "score": 0.325,
      "components": {
        "momentum_5d": -0.086,
        "momentum_10d": 0.278,
        "momentum_20d": 0.4,
        "relative_strength": 0.795,
        "volume_expansion": 0.177,
        "breakout_flag": 0.0,
        "trend_filter": 1.0,
        "volatility_penalty": -0.0
      },
      "atr_pct": 0.0343,
      "tradeable": false,
      "reason": "long_setup: mom20=+20.0%, RS=+15.9%, uptrend",
      "bucket": "ai_nasdaq_semis"
    },
    {
      "ticker": "XOM",
      "score": 0.305,
      "components": {
        "momentum_5d": 0.469,
        "momentum_10d": 0.101,
        "momentum_20d": 0.157,
        "relative_strength": 0.187,
        "volume_expansion": 0.296,
        "breakout_flag": 1.0,
        "trend_filter": 0.0,
        "volatility_penalty": -0.0
      },
      "atr_pct": 0.0261,
      "tradeable": false,
      "reason": "long_setup: mom20=+7.8%, RS=+3.7%, vol 1.6×, breakout",
      "bucket": "inflation_energy"
    },
    {
      "ticker": "NVDA",
      "score": 0.283,
      "components": {
        "momentum_5d": 0.235,
        "momentum_10d": 0.407,
        "momentum_20d": 0.234,
        "relative_strength": 0.381,
        "volume_expansion": -0.067,
        "breakout_flag": 0.0,
        "trend_filter": 1.0,
        "volatility_penalty": -0.0
      },
      "atr_pct": 0.0388,
      "tradeable": false,
      "reason": "long_setup: mom20=+11.7%, RS=+7.6%, uptrend",
      "bucket": "ai_nasdaq_semis"
    },
    {
      "ticker": "XLE",
      "score": 0.236,
      "components": {
        "momentum_5d": 0.338,
        "momentum_10d": 0.032,
        "momentum_20d": 0.162,
        "relative_strength": 0.201,
        "volume_expansion": -0.024,
        "breakout_flag": 1.0,
        "trend_filter": 0.0,
        "volatility_penalty": -0.0
      },
      "atr_pct": 0.023,
      "tradeable": false,
      "reason": "long_setup: mom20=+8.1%, RS=+4.0%, breakout",
      "bucket": "inflation_energy"
    },
    {
      "ticker": "AAPL",
      "score": 0.217,
      "components": {
        "momentum_5d": 0.12,
        "momentum_10d": 0.215,
        "momentum_20d": 0.222,
        "relative_strength": 0.35,
        "volume_expansion": -0.032,
        "breakout_flag": 0.0,
        "trend_filter": 1.0,
        "volatility_penalty": -0.0
      },
      "atr_pct": 0.0236,
      "tradeable": false,
      "reason": "long_setup: mom20=+11.1%, RS=+7.0%, uptrend",
      "bucket": "ai_nasdaq_semis"
    },
    {
      "ticker": "GOOGL",
      "score": 0.205,
      "components": {
        "momentum_5d": -0.049,
        "momentum_10d": 0.085,
        "momentum_20d": 0.322,
        "relative_strength": 0.601,
        "volume_expansion": -0.209,
        "breakout_flag": 0.0,
        "trend_filter": 1.0,
        "volatility_penalty": -0.0
      },
      "atr_pct": 0.0295,
      "tradeable": false,
      "reason": "long_setup: mom20=+16.1%, RS=+12.0%, uptrend",
      "bucket": "ai_nasdaq_semis"
    },
    {
      "ticker": "QQQ",
      "score": 0.164,
      "components": {
        "momentum_5d": -0.016,
        "momentum_10d": 0.155,
        "momentum_20d": 0.186,
        "relative_strength": 0.259,
        "volume_expansion": 0.063,
        "breakout_flag": 0.0,
        "trend_filter": 1.0,
        "volatility_penalty": -0.0
      },
      "atr_pct": 0.0156,
      "tradeable": false,
      "reason": "long_setup: mom20=+9.3%, RS=+5.2%, uptrend",
      "bucket": "ai_nasdaq_semis"
    },
    {
      "ticker": "CVX",
      "score": 0.155,
      "components": {
        "momentum_5d": 0.265,
        "momentum_10d": 0.007,
        "momentum_20d": 0.077,
        "relative_strength": -0.011,
        "volume_expansion": -0.084,
        "breakout_flag": 1.0,
        "trend_filter": 0.0,
        "volatility_penalty": -0.0
      },
      "atr_pct": 0.0225,
      "tradeable": false,
      "reason": "long_setup: breakout",
      "bucket": "inflation_energy"
    },
    {
      "ticker": "MSFT",
      "score": 0.149,
      "components": {
        "momentum_5d": 0.085,
        "momentum_10d": 0.055,
        "momentum_20d": -0.004,
        "relative_strength": -0.213,
        "volume_expansion": 0.143,
        "breakout_flag": 1.0,
        "trend_filter": 1.0,
        "volatility_penalty": -0.0
      },
      "atr_pct": 0.0272,
      "tradeable": false,
      "reason": "long_setup: RS=-4.3%, breakout, uptrend",
      "bucket": "ai_nasdaq_semis"
    },
    {
      "ticker": "TSLA",
      "score": 0.11,
      "components": {
        "momentum_5d": -0.071,
        "momentum_10d": 0.242,
        "momentum_20d": 0.108,
        "relative_strength": 0.065,
        "volume_expansion": -0.041,
        "breakout_flag": 0.0,
        "trend_filter": 1.0,
        "volatility_penalty": -0.0
      },
      "atr_pct": 0.0427,
      "tradeable": false,
      "reason": "long_setup: mom20=+5.4%, uptrend",
      "bucket": "ai_nasdaq_semis"
    },
    {
      "ticker": "AVGO",
      "score": 0.048,
      "components": {
        "momentum_5d": -0.056,
        "momentum_10d": 0.027,
        "momentum_20d": 0.091,
        "relative_strength": 0.023,
        "volume_expansion": -0.144,
        "breakout_flag": 0.0,
        "trend_filter": 1.0,
        "volatility_penalty": -0.0
      },
      "atr_pct": 0.0403,
      "tradeable": false,
      "reason": "long_setup: uptrend",
      "bucket": "ai_nasdaq_semis"
    },
    {
      "ticker": "AMZN",
      "score": -0.009,
      "components": {
        "momentum_5d": -0.153,
        "momentum_10d": -0.046,
        "momentum_20d": 0.11,
        "relative_strength": 0.07,
        "volume_expansion": -0.001,
        "breakout_flag": 0.0,
        "trend_filter": 0.0,
        "volatility_penalty": -0.0
      },
      "atr_pct": 0.0268,
      "tradeable": false,
      "reason": "short_setup: mom20=+5.5%",
      "bucket": "ai_nasdaq_semis"
    }
  ],
  "target_weights": {
    "USO": 0.18,
    "AMD": 0.18,
    "OXY": 0.18,
    "SPY": 0.1,
    "QQQ": 0.1,
    "GLD": 0.1
  },
  "allocation_reason": "regime=NEUTRAL | primary_picks=3(54%) | fallback=['SPY', 'QQQ', 'GLD'] | unfilled=16.00%",
  "invested_ratio_after_target": 0.84,
  "current_weights": {
    "AMD": 0.1489,
    "GLD": 0.1957,
    "NVDA": 0.1534,
    "QQQ": 0.166,
    "SMH": 0.1538,
    "SPY": 0.1892
  },
  "rebalance_orders": [
    {
      "symbol": "USO",
      "action": "BUY",
      "asset_class": "us_equity",
      "current_value": 0.0,
      "target_value": 16881.47,
      "delta": 16881.47,
      "current_qty": 0.0,
      "qty_delta": null,
      "current_price": null,
      "reason": "new position at target 18.0%"
    },
    {
      "symbol": "OXY",
      "action": "BUY",
      "asset_class": "us_equity",
      "current_value": 0.0,
      "target_value": 16881.47,
      "delta": 16881.47,
      "current_qty": 0.0,
      "qty_delta": null,
      "current_price": null,
      "reason": "new position at target 18.0%"
    },
    {
      "symbol": "SMH",
      "action": "EXIT",
      "asset_class": "us_equity",
      "current_value": 14425.58,
      "target_value": 0.0,
      "delta": -14425.58,
      "current_qty": 26.0,
      "qty_delta": -26.0,
      "current_price": 554.83,
      "reason": "symbol not in target allocation"
    },
    {
      "symbol": "NVDA",
      "action": "EXIT",
      "asset_class": "us_equity",
      "current_value": 14386.56,
      "target_value": 0.0,
      "delta": -14386.56,
      "current_qty": 64.0,
      "qty_delta": -64.0,
      "current_price": 224.79,
      "reason": "symbol not in target allocation"
    },
    {
      "symbol": "GLD",
      "action": "REDUCE",
      "asset_class": "us_equity",
      "current_value": 18350.2,
      "target_value": 9378.59,
      "delta": -8971.61,
      "current_qty": 44.0,
      "qty_delta": -21.512068,
      "current_price": 417.05,
      "reason": "reduce $8972 to target 10.0%"
    },
    {
      "symbol": "SPY",
      "action": "REDUCE",
      "asset_class": "us_equity",
      "current_value": 17740.08,
      "target_value": 9378.59,
      "delta": -8361.49,
      "current_qty": 24.0,
      "qty_delta": -11.311996,
      "current_price": 739.17,
      "reason": "reduce $8361 to target 10.0%"
    },
    {
      "symbol": "QQQ",
      "action": "REDUCE",
      "asset_class": "us_equity",
      "current_value": 15568.74,
      "target_value": 9378.59,
      "delta": -6190.15,
      "current_qty": 22.0,
      "qty_delta": -8.747224,
      "current_price": 707.67,
      "reason": "reduce $6190 to target 10.0%"
    },
    {
      "symbol": "AMD",
      "action": "BUY",
      "asset_class": "us_equity",
      "current_value": 13962.3,
      "target_value": 16881.47,
      "delta": 2919.17,
      "current_qty": 33.0,
      "qty_delta": 6.89947,
      "current_price": 423.1,
      "reason": "add $2919 to reach target 18.0%"
    }
  ],
  "risk_checks": {
    "passed": [
      "AMD:BUY",
      "GLD:REDUCE",
      "NVDA:EXIT",
      "QQQ:REDUCE",
      "SMH:EXIT",
      "SPY:REDUCE",
      "USO:BUY",
      "OXY:BUY"
    ],
    "failed": [],
    "n_orders": 8,
    "n_hold": 0
  },
  "learning_loop_ref": "2026-05-15",
  "trace_log_lines": 44
}