{
  "components": [
    {
      "age_seconds": 139.41153,
      "component": "crypto-monitor",
      "last_seen_iso": "2026-06-28T08:00:32.428539+00:00",
      "status": "FRESH",
      "threshold_seconds": 86400
    },
    {
      "age_seconds": 441.142121,
      "component": "defense-monitor",
      "last_seen_iso": "2026-06-28T07:55:30.697948+00:00",
      "status": "FRESH",
      "threshold_seconds": 86400
    },
    {
      "age_seconds": 135.19435,
      "component": "twitter-monitor",
      "last_seen_iso": "2026-06-28T08:00:36.645719+00:00",
      "status": "FRESH",
      "threshold_seconds": 86400
    },
    {
      "age_seconds": null,
      "component": "reddit-monitor",
      "last_seen_iso": null,
      "status": "MISSING",
      "threshold_seconds": 86400
    },
    {
      "age_seconds": 140.835164,
      "component": "geo-monitor",
      "last_seen_iso": "2026-06-28T08:00:31.004905+00:00",
      "status": "FRESH",
      "threshold_seconds": 86400
    },
    {
      "age_seconds": 2818.420916,
      "component": "politician-monitor",
      "last_seen_iso": "2026-06-28T07:15:53.419153+00:00",
      "status": "FRESH",
      "threshold_seconds": 86400
    },
    {
      "age_seconds": null,
      "component": "options-monitor",
      "last_seen_iso": null,
      "status": "MISSING",
      "threshold_seconds": 86400
    },
    {
      "age_seconds": 147.729428,
      "component": "options-exit-monitor",
      "last_seen_iso": "2026-06-28T08:00:24.110641+00:00",
      "status": "FRESH",
      "threshold_seconds": 86400
    },
    {
      "age_seconds": null,
      "component": "price-monitor",
      "last_seen_iso": null,
      "status": "MISSING",
      "threshold_seconds": 86400
    },
    {
      "age_seconds": 447.971815,
      "component": "exit-monitor",
      "last_seen_iso": "2026-06-28T07:55:23.868254+00:00",
      "status": "FRESH",
      "threshold_seconds": 86400
    },
    {
      "age_seconds": null,
      "component": "incident-pattern-detector",
      "last_seen_iso": null,
      "status": "MISSING",
      "threshold_seconds": 86400
    }
  ],
  "exit_code": 0,
  "generated_at_iso": "2026-06-28T08:02:51.840069+00:00",
  "market_open": false,
  "market_reason": "weekend",
  "summary": {
    "fresh": 7,
    "missing": 4,
    "stale": 0,
    "total": 11
  },
  "threshold_seconds": 86400,
  "thresholds": {
    "market_session_stale_seconds": 7200,
    "non_market_stale_seconds": 86400
  },
  "version": "v3.22.0"
}