{
  "_last_writer": "heartbeat",
  "heartbeat": {
    "crypto-monitor": {
      "last_message": "scanned 11 coins",
      "last_seen_iso": "2026-07-01T21:05:27.273959+00:00",
      "last_status": "ok",
      "pings_today": 20
    },
    "defense-monitor": {
      "last_message": "",
      "last_seen_iso": "2026-07-01T20:55:35.329715+00:00",
      "last_status": "ok",
      "pings_today": 14
    },
    "doj-monitor": {
      "last_message": "emitted=0",
      "last_seen_iso": "2026-07-01T19:27:28.976682+00:00",
      "last_status": "ok",
      "pings_today": 1
    },
    "exit-monitor": {
      "last_message": "",
      "last_seen_iso": "2026-07-01T21:08:00.243597+00:00",
      "last_status": "ok",
      "pings_today": 19
    },
    "geo-monitor": {
      "last_message": "",
      "last_seen_iso": "2026-07-01T20:30:31.593685+00:00",
      "last_status": "ok",
      "pings_today": 3
    },
    "options-exit-monitor": {
      "last_message": "",
      "last_seen_iso": "2026-07-01T21:05:26.513246+00:00",
      "last_status": "ok",
      "pings_today": 16
    },
    "options-monitor": {
      "last_message": "",
      "last_seen_iso": "2026-07-01T20:59:31.940456+00:00",
      "last_status": "ok",
      "pings_today": 1
    },
    "politician-monitor": {
      "last_message": "emitted=0",
      "last_seen_iso": "2026-07-01T19:59:04.996958+00:00",
      "last_status": "ok",
      "pings_today": 1
    },
    "price-monitor": {
      "last_message": "",
      "last_seen_iso": "2026-07-01T20:59:49.256001+00:00",
      "last_status": "ok",
      "pings_today": 1
    },
    "reddit-monitor": {
      "last_message": "sent=0",
      "last_seen_iso": "2026-07-01T20:49:55.595346+00:00",
      "last_status": "ok",
      "pings_today": 1
    },
    "twitter-monitor": {
      "last_message": "",
      "last_seen_iso": "2026-07-01T21:05:39.900828+00:00",
      "last_status": "ok",
      "pings_today": 15
    }
  },
  "intraday_governor": {
    "account_unavailable": false,
    "alerts_sent": {},
    "block_new_entries": false,
    "current_equity": 90504.88,
    "current_intraday_pnl": 0.0,
    "current_intraday_pnl_pct": 0.0,
    "date": "2026-07-01",
    "giveback_pct_of_peak": 0.0,
    "giveback_usd": 0.0,
    "intraday_peak_equity": 90504.88,
    "intraday_peak_pnl": 0.0,
    "intraday_peak_pnl_pct": 0.0,
    "last_action": "noop",
    "last_update_at": "2026-07-01T21:08:00.239193+00:00",
    "max_gross_target": 1.5,
    "options_first_reduction": false,
    "peak_at": "2026-07-01T19:35:26.206841+00:00",
    "pnl_state": "FLAT",
    "profit_floor_usd": 0.0,
    "session_start_equity": 90504.88,
    "state_entered_at": "2026-07-01T19:35:26.206841+00:00",
    "top_giveback_symbols": []
  }
}