{
  "_last_writer": "heartbeat",
  "heartbeat": {
    "crypto-monitor": {
      "last_message": "scanned 11 coins",
      "last_seen_iso": "2026-07-01T12:10:33.375731+00:00",
      "last_status": "ok",
      "pings_today": 21
    },
    "defense-monitor": {
      "last_message": "",
      "last_seen_iso": "2026-07-01T12:10:31.419375+00:00",
      "last_status": "ok",
      "pings_today": 11
    },
    "exit-monitor": {
      "last_message": "",
      "last_seen_iso": "2026-07-01T11:55:29.110868+00:00",
      "last_status": "ok",
      "pings_today": 17
    },
    "geo-monitor": {
      "last_message": "",
      "last_seen_iso": "2026-07-01T11:30:30.494719+00:00",
      "last_status": "ok",
      "pings_today": 1
    },
    "options-exit-monitor": {
      "last_message": "",
      "last_seen_iso": "2026-07-01T12:10:26.138525+00:00",
      "last_status": "ok",
      "pings_today": 19
    },
    "twitter-monitor": {
      "last_message": "",
      "last_seen_iso": "2026-07-01T12:05:36.320370+00:00",
      "last_status": "ok",
      "pings_today": 10
    }
  },
  "intraday_governor": {
    "account_unavailable": false,
    "alerts_sent": {},
    "block_new_entries": false,
    "current_equity": 90504.88,
    "current_intraday_pnl": 0.0,
    "current_intraday_pnl_pct": 0.0,
    "date": "2026-07-01",
    "giveback_pct_of_peak": 0.0,
    "giveback_usd": 0.0,
    "intraday_peak_equity": 90504.88,
    "intraday_peak_pnl": 0.0,
    "intraday_peak_pnl_pct": 0.0,
    "last_action": "noop",
    "last_update_at": "2026-07-01T11:55:29.107271+00:00",
    "max_gross_target": 1.5,
    "options_first_reduction": false,
    "peak_at": "2026-07-01T10:25:27.296303+00:00",
    "pnl_state": "FLAT",
    "profit_floor_usd": 0.0,
    "session_start_equity": 90504.88,
    "state_entered_at": "2026-07-01T10:25:27.296303+00:00",
    "top_giveback_symbols": []
  }
}