{
  "generated_at": "2026-05-18T16:46:29.044104+00:00",
  "workflows": [
    {
      "workflow_file": "price-monitor.yml",
      "label": "price-monitor",
      "asset_class": "us_equity",
      "expected_cadence_min": 5,
      "manual_only": false,
      "in_active_window": true,
      "runs_total_returned": 20,
      "last_run_id": 26046125763,
      "last_run_status": "completed",
      "last_run_conclusion": "success",
      "last_run_url": "https://github.com/mikosbartlomiej-prog/trading-system/actions/runs/26046125763",
      "last_run_ts": "2026-05-18T16:23:47Z",
      "last_run_event": "schedule",
      "minutes_since_last_run": 22,
      "staleness_ratio": 4.4,
      "runs_last_24h": 2,
      "successes_last_24h": 2,
      "failures_last_24h": 0,
      "success_rate_last_24h": 1.0,
      "observed_cadence_min": 94.2,
      "cadence_drift_ratio": 18.84,
      "status": "STALE"
    },
    {
      "workflow_file": "crypto-monitor.yml",
      "label": "crypto-monitor",
      "asset_class": "crypto",
      "expected_cadence_min": 5,
      "manual_only": false,
      "in_active_window": true,
      "runs_total_returned": 20,
      "last_run_id": 26045820538,
      "last_run_status": "completed",
      "last_run_conclusion": "success",
      "last_run_url": "https://github.com/mikosbartlomiej-prog/trading-system/actions/runs/26045820538",
      "last_run_ts": "2026-05-18T16:17:45Z",
      "last_run_event": "schedule",
      "minutes_since_last_run": 28,
      "staleness_ratio": 5.6,
      "runs_last_24h": 14,
      "successes_last_24h": 14,
      "failures_last_24h": 0,
      "success_rate_last_24h": 1.0,
      "observed_cadence_min": 119.2,
      "cadence_drift_ratio": 23.84,
      "status": "STALE"
    },
    {
      "workflow_file": "defense-monitor.yml",
      "label": "defense-monitor",
      "asset_class": "us_equity",
      "expected_cadence_min": 5,
      "manual_only": false,
      "in_active_window": true,
      "runs_total_returned": 20,
      "last_run_id": 26046276692,
      "last_run_status": "completed",
      "last_run_conclusion": "success",
      "last_run_url": "https://github.com/mikosbartlomiej-prog/trading-system/actions/runs/26046276692",
      "last_run_ts": "2026-05-18T16:26:46Z",
      "last_run_event": "schedule",
      "minutes_since_last_run": 19,
      "staleness_ratio": 3.8,
      "runs_last_24h": 20,
      "successes_last_24h": 16,
      "failures_last_24h": 0,
      "success_rate_last_24h": 0.8,
      "observed_cadence_min": 6.7,
      "cadence_drift_ratio": 1.34,
      "status": "STALE"
    },
    {
      "workflow_file": "geo-monitor.yml",
      "label": "geo-monitor",
      "asset_class": "us_equity",
      "expected_cadence_min": 15,
      "manual_only": false,
      "in_active_window": true,
      "runs_total_returned": 20,
      "last_run_id": 26045665910,
      "last_run_status": "completed",
      "last_run_conclusion": "success",
      "last_run_url": "https://github.com/mikosbartlomiej-prog/trading-system/actions/runs/26045665910",
      "last_run_ts": "2026-05-18T16:14:41Z",
      "last_run_event": "schedule",
      "minutes_since_last_run": 31,
      "staleness_ratio": 2.07,
      "runs_last_24h": 11,
      "successes_last_24h": 11,
      "failures_last_24h": 0,
      "success_rate_last_24h": 1.0,
      "observed_cadence_min": 71.4,
      "cadence_drift_ratio": 4.76,
      "status": "HEALTHY"
    },
    {
      "workflow_file": "reddit-monitor.yml",
      "label": "reddit-monitor",
      "asset_class": "mixed",
      "expected_cadence_min": 30,
      "manual_only": false,
      "in_active_window": true,
      "runs_total_returned": 20,
      "last_run_id": 26046184619,
      "last_run_status": "completed",
      "last_run_conclusion": "success",
      "last_run_url": "https://github.com/mikosbartlomiej-prog/trading-system/actions/runs/26046184619",
      "last_run_ts": "2026-05-18T16:24:58Z",
      "last_run_event": "schedule",
      "minutes_since_last_run": 21,
      "staleness_ratio": 0.7,
      "runs_last_24h": 12,
      "successes_last_24h": 12,
      "failures_last_24h": 0,
      "success_rate_last_24h": 1.0,
      "observed_cadence_min": 68.8,
      "cadence_drift_ratio": 2.29,
      "status": "HEALTHY"
    },
    {
      "workflow_file": "twitter-monitor.yml",
      "label": "twitter-monitor",
      "asset_class": "mixed",
      "expected_cadence_min": 5,
      "manual_only": false,
      "in_active_window": true,
      "runs_total_returned": 20,
      "last_run_id": 26045938038,
      "last_run_status": "completed",
      "last_run_conclusion": "success",
      "last_run_url": "https://github.com/mikosbartlomiej-prog/trading-system/actions/runs/26045938038",
      "last_run_ts": "2026-05-18T16:20:07Z",
      "last_run_event": "workflow_dispatch",
      "minutes_since_last_run": 26,
      "staleness_ratio": 5.2,
      "runs_last_24h": 18,
      "successes_last_24h": 18,
      "failures_last_24h": 0,
      "success_rate_last_24h": 1.0,
      "observed_cadence_min": 120.0,
      "cadence_drift_ratio": 24.0,
      "status": "STALE"
    },
    {
      "workflow_file": "options-monitor.yml",
      "label": "options-monitor",
      "asset_class": "us_option",
      "expected_cadence_min": 5,
      "manual_only": false,
      "in_active_window": true,
      "runs_total_returned": 20,
      "last_run_id": 26046008806,
      "last_run_status": "completed",
      "last_run_conclusion": "success",
      "last_run_url": "https://github.com/mikosbartlomiej-prog/trading-system/actions/runs/26046008806",
      "last_run_ts": "2026-05-18T16:21:30Z",
      "last_run_event": "schedule",
      "minutes_since_last_run": 24,
      "staleness_ratio": 4.8,
      "runs_last_24h": 2,
      "successes_last_24h": 2,
      "failures_last_24h": 0,
      "success_rate_last_24h": 1.0,
      "observed_cadence_min": 93.8,
      "cadence_drift_ratio": 18.76,
      "status": "STALE"
    },
    {
      "workflow_file": "options-exit-monitor.yml",
      "label": "options-exit-monitor",
      "asset_class": "us_option",
      "expected_cadence_min": 5,
      "manual_only": false,
      "in_active_window": true,
      "runs_total_returned": 20,
      "last_run_id": 26046471951,
      "last_run_status": "completed",
      "last_run_conclusion": "success",
      "last_run_url": "https://github.com/mikosbartlomiej-prog/trading-system/actions/runs/26046471951",
      "last_run_ts": "2026-05-18T16:30:35Z",
      "last_run_event": "schedule",
      "minutes_since_last_run": 15,
      "staleness_ratio": 3.0,
      "runs_last_24h": 2,
      "successes_last_24h": 2,
      "failures_last_24h": 0,
      "success_rate_last_24h": 1.0,
      "observed_cadence_min": 92.3,
      "cadence_drift_ratio": 18.46,
      "status": "HEALTHY"
    },
    {
      "workflow_file": "exit-monitor.yml",
      "label": "exit-monitor",
      "asset_class": "mixed",
      "expected_cadence_min": 5,
      "manual_only": false,
      "in_active_window": true,
      "runs_total_returned": 20,
      "last_run_id": 26046472310,
      "last_run_status": "completed",
      "last_run_conclusion": "success",
      "last_run_url": "https://github.com/mikosbartlomiej-prog/trading-system/actions/runs/26046472310",
      "last_run_ts": "2026-05-18T16:30:35Z",
      "last_run_event": "schedule",
      "minutes_since_last_run": 15,
      "staleness_ratio": 3.0,
      "runs_last_24h": 20,
      "successes_last_24h": 20,
      "failures_last_24h": 0,
      "success_rate_last_24h": 1.0,
      "observed_cadence_min": 109.6,
      "cadence_drift_ratio": 21.92,
      "status": "HEALTHY"
    },
    {
      "workflow_file": "daily-learning.yml",
      "label": "daily-learning",
      "asset_class": "ops",
      "expected_cadence_min": 1440,
      "manual_only": false,
      "in_active_window": false,
      "runs_total_returned": 20,
      "last_run_id": 26021231080,
      "last_run_status": "completed",
      "last_run_conclusion": "success",
      "last_run_url": "https://github.com/mikosbartlomiej-prog/trading-system/actions/runs/26021231080",
      "last_run_ts": "2026-05-18T08:05:29Z",
      "last_run_event": "schedule",
      "minutes_since_last_run": 521,
      "staleness_ratio": 0.36,
      "runs_last_24h": 2,
      "successes_last_24h": 2,
      "failures_last_24h": 0,
      "success_rate_last_24h": 1.0,
      "observed_cadence_min": 398.4,
      "cadence_drift_ratio": 0.28,
      "status": "OFF_HOURS"
    },
    {
      "workflow_file": "weekly-retro.yml",
      "label": "weekly-retro",
      "asset_class": "ops",
      "expected_cadence_min": 10080,
      "manual_only": false,
      "in_active_window": false,
      "runs_total_returned": 2,
      "last_run_id": 26004881683,
      "last_run_status": "completed",
      "last_run_conclusion": "failure",
      "last_run_url": "https://github.com/mikosbartlomiej-prog/trading-system/actions/runs/26004881683",
      "last_run_ts": "2026-05-17T22:43:21Z",
      "last_run_event": "schedule",
      "minutes_since_last_run": 1083,
      "staleness_ratio": 0.11,
      "runs_last_24h": 1,
      "successes_last_24h": 0,
      "failures_last_24h": 1,
      "success_rate_last_24h": 0.0,
      "observed_cadence_min": 10086.7,
      "cadence_drift_ratio": 1.0,
      "last_failure_id": 26004881683,
      "last_failure_url": "https://github.com/mikosbartlomiej-prog/trading-system/actions/runs/26004881683",
      "last_failure_ts": "2026-05-17T22:43:21Z",
      "status": "FAILING"
    },
    {
      "workflow_file": "auto-merge.yml",
      "label": "auto-merge",
      "asset_class": "ops",
      "expected_cadence_min": null,
      "manual_only": true,
      "in_active_window": true,
      "runs_total_returned": 20,
      "last_run_id": 26046341404,
      "last_run_status": "completed",
      "last_run_conclusion": "success",
      "last_run_url": "https://github.com/mikosbartlomiej-prog/trading-system/actions/runs/26046341404",
      "last_run_ts": "2026-05-18T16:28:04Z",
      "last_run_event": "push",
      "minutes_since_last_run": 18,
      "runs_last_24h": 13,
      "successes_last_24h": 12,
      "failures_last_24h": 0,
      "success_rate_last_24h": 0.92,
      "observed_cadence_min": 70.7,
      "status": "MANUAL_ONLY"
    },
    {
      "workflow_file": "keep-alive.yml",
      "label": "keep-alive",
      "asset_class": "ops",
      "expected_cadence_min": null,
      "manual_only": false,
      "in_active_window": true,
      "runs_total_returned": 20,
      "last_run_id": 25786921212,
      "last_run_status": "completed",
      "last_run_conclusion": "success",
      "last_run_url": "https://github.com/mikosbartlomiej-prog/trading-system/actions/runs/25786921212",
      "last_run_ts": "2026-05-13T08:13:34Z",
      "last_run_event": "schedule",
      "minutes_since_last_run": 7712,
      "runs_last_24h": 0,
      "successes_last_24h": 0,
      "failures_last_24h": 0,
      "observed_cadence_min": 113.6,
      "status": "HEALTHY"
    },
    {
      "workflow_file": "snapshot.yml",
      "label": "snapshot",
      "asset_class": "ops",
      "expected_cadence_min": null,
      "manual_only": true,
      "in_active_window": true,
      "runs_total_returned": 0,
      "status": "NO_RUNS"
    }
  ]
}